haystack_translate_node/__init__.py
haystack_translate_node-0.0.1.dist-info/METADATA
haystack_translate_node-0.0.1.dist-info/WHEEL
haystack_translate_node-0.0.1.dist-info/licenses/LICENSE.md
haystack_translate_node-0.0.1.dist-info/RECORD
