Metadata-Version: 2.1
Name: haystack_translate_node
Version: 0.0.1
Summary: An Azure Translate node for Deepset Haystack
Project-URL: Homepage, https://github.com/recrudesce/haystack_translate_node
Project-URL: Bug Tracker, https://github.com/recrudesce/haystack_translate_node/issues
Author-email: recrudesce <recrudesce@gmail.com>
License-File: LICENSE.md
Classifier: License :: OSI Approved :: MIT License
Classifier: Operating System :: OS Independent
Classifier: Programming Language :: Python :: 3
Requires-Python: >=3.10
Requires-Dist: farm-haystack
